{
    "messageType": "BSM",
    "messageId": "3_676",
    "messageCount": 676,
    "vehicleId": "3",
    "timestamp": "2024-10-16T04:23:57Z",
    "position": {
        "latitude": 37.77210404584901,
        "longitude": -122.42690497135406,
        "altitude": 16.548796971766436
    },
    "speed": 94.86129456157663,
    "heading": 152.20293807172013,
    "acceleration": {
        "x": -0.809493917640735,
        "y": 0.5712896541708599,
        "z": 0.3162482759767363
    },
    "brakeStatus": true,
    "vehicleSize": {
        "length": 4.266091277513892,
        "width": 2.101819121188857
    },
    "pathHistory": [
        {
            "timestamp": "2024-10-16T04:23:27Z",
            "position": {
                "latitude": 37.77219603621993,
                "longitude": -122.42694998554362
            }
        },
        {
            "timestamp": "2024-10-16T04:22:57Z",
            "position": {
                "latitude": 37.77195515247668,
                "longitude": -122.42683003200426
            }
        }
    ],
    "pathPrediction": {
        "timestamp": "2024-10-16T04:24:12Z",
        "position": {
            "latitude": 37.772563111683816,
            "longitude": -122.42737614318683
        },
        "confidence": 0.6259836923876172
    }
}