{
    "messageType": "BSM",
    "messageId": "4_710",
    "messageCount": 710,
    "vehicleId": "4",
    "timestamp": "2024-10-16T04:23:17Z",
    "position": {
        "latitude": 37.76830309824713,
        "longitude": -122.42695319328041,
        "altitude": 13.629762199514833
    },
    "speed": 39.703110128628325,
    "heading": 66.7514897042745,
    "acceleration": {
        "x": -0.28234972328747676,
        "y": 0.2937249155172268,
        "z": 0.08888664813748981
    },
    "brakeStatus": true,
    "vehicleSize": {
        "length": 4.712123515569847,
        "width": 2.0075264436316376
    },
    "pathHistory": [
        {
            "timestamp": "2024-10-16T04:22:47Z",
            "position": {
                "latitude": 37.76825616975148,
                "longitude": -122.4269293252092
            }
        },
        {
            "timestamp": "2024-10-16T04:22:17Z",
            "position": {
                "latitude": 37.768275470921076,
                "longitude": -122.42682474204256
            }
        }
    ],
    "pathPrediction": {
        "timestamp": "2024-10-16T04:23:32Z",
        "position": {
            "latitude": 37.76867037301657,
            "longitude": -122.42697723244282
        },
        "confidence": 0.9252279985497501
    }
}