{
    "messageType": "BSM",
    "messageId": "7_63",
    "messageCount": 63,
    "vehicleId": "7",
    "timestamp": "2024-10-16T04:21:18Z",
    "position": {
        "latitude": 37.76750144024413,
        "longitude": -122.42909576336818,
        "altitude": 10.852781419610336
    },
    "speed": 56.30776506380776,
    "heading": 293.48684583534595,
    "acceleration": {
        "x": 0.7638948148810467,
        "y": -0.1345980176927286,
        "z": -0.3351774594273558
    },
    "brakeStatus": false,
    "vehicleSize": {
        "length": 4.189607015098218,
        "width": 1.9893910281876055
    },
    "pathHistory": [
        {
            "timestamp": "2024-10-16T04:20:48Z",
            "position": {
                "latitude": 37.767482086663726,
                "longitude": -122.42914851180412
            }
        },
        {
            "timestamp": "2024-10-16T04:20:18Z",
            "position": {
                "latitude": 37.76741680321265,
                "longitude": -122.42920947762279
            }
        }
    ],
    "pathPrediction": {
        "timestamp": "2024-10-16T04:21:33Z",
        "position": {
            "latitude": 37.768017566252475,
            "longitude": -122.42959885718037
        },
        "confidence": 0.8467378057567752
    }
}