{
    "messageType": "BSM",
    "messageId": "7_879",
    "messageCount": 879,
    "vehicleId": "7",
    "timestamp": "2024-10-16T04:22:46Z",
    "position": {
        "latitude": 37.78458879487994,
        "longitude": -122.41775715239693,
        "altitude": 19.256792981763205
    },
    "speed": 22.429572655945805,
    "heading": 351.31487481057894,
    "acceleration": {
        "x": -0.9733677511527681,
        "y": -0.6992488185133605,
        "z": -0.45769417547115454
    },
    "brakeStatus": false,
    "vehicleSize": {
        "length": 4.446277909777018,
        "width": 2.3652706124313667
    },
    "pathHistory": [
        {
            "timestamp": "2024-10-16T04:22:16Z",
            "position": {
                "latitude": 37.784599992905065,
                "longitude": -122.41783444359011
            }
        },
        {
            "timestamp": "2024-10-16T04:21:46Z",
            "position": {
                "latitude": 37.78447133189928,
                "longitude": -122.41775424660453
            }
        }
    ],
    "pathPrediction": {
        "timestamp": "2024-10-16T04:23:01Z",
        "position": {
            "latitude": 37.78370312287387,
            "longitude": -122.41873404841265
        },
        "confidence": 0.9094351047608109
    }
}