{
    "messageType": "BSM",
    "messageId": "7_181",
    "messageCount": 181,
    "vehicleId": "7",
    "timestamp": "2024-10-16T04:22:25Z",
    "position": {
        "latitude": 37.775798594857974,
        "longitude": -122.41147463221445,
        "altitude": 14.667575130439236
    },
    "speed": 19.299589085477486,
    "heading": 107.76020994100722,
    "acceleration": {
        "x": -0.7520334200440622,
        "y": -0.35685786165051314,
        "z": -0.3174112106313225
    },
    "brakeStatus": true,
    "vehicleSize": {
        "length": 4.907989572913856,
        "width": 2.2620852049835465
    },
    "pathHistory": [
        {
            "timestamp": "2024-10-16T04:21:55Z",
            "position": {
                "latitude": 37.775830700928545,
                "longitude": -122.4115343576241
            }
        },
        {
            "timestamp": "2024-10-16T04:21:25Z",
            "position": {
                "latitude": 37.77568357929439,
                "longitude": -122.41145474426938
            }
        }
    ],
    "pathPrediction": {
        "timestamp": "2024-10-16T04:22:40Z",
        "position": {
            "latitude": 37.776616847630315,
            "longitude": -122.41128089300844
        },
        "confidence": 0.9994975055090634
    }
}