{
    "messageType": "BSM",
    "messageId": "V8_927",
    "messageCount": 927,
    "vehicleId": "V8",
    "timestamp": "2024-11-03T16:11:13Z",
    "position": {
        "latitude": 37.7758694053786,
        "longitude": -122.42097208560153,
        "altitude": 12.775038302901546
    },
    "speed": 53.36091024238565,
    "heading": 256.8983132785752,
    "acceleration": {
        "x": -0.803187621593463,
        "y": -0.23525958916904433,
        "z": -0.24233104363447988
    },
    "brakeStatus": true,
    "vehicleSize": {
        "length": 4.124395265856282,
        "width": 2.4152999484574886
    },
    "pathHistory": [
        {
            "timestamp": "2024-11-03T16:10:43Z",
            "position": {
                "latitude": 37.77580461777255,
                "longitude": -122.42091069868754
            }
        },
        {
            "timestamp": "2024-11-03T16:10:13Z",
            "position": {
                "latitude": 37.77585122008105,
                "longitude": -122.42105843985651
            }
        }
    ],
    "pathPrediction": {
        "position": {
            "latitude": 37.77677214462446,
            "longitude": -122.42070166322996
        },
        "confidence": 0.8239978672372958
    }
}