{
    "messageType": "BSM",
    "messageId": "9_291",
    "messageCount": 291,
    "vehicleId": "9",
    "timestamp": "2024-10-16T04:21:21Z",
    "position": {
        "latitude": 37.77955219719119,
        "longitude": -122.42118236208907,
        "altitude": 11.888202256321186
    },
    "speed": 10.915964262747135,
    "heading": 277.1700192214193,
    "acceleration": {
        "x": -0.33001477797325274,
        "y": 0.3839224183037784,
        "z": -0.1077796114849735
    },
    "brakeStatus": true,
    "vehicleSize": {
        "length": 3.904261448053596,
        "width": 2.073891498579598
    },
    "pathHistory": [
        {
            "timestamp": "2024-10-16T04:20:51Z",
            "position": {
                "latitude": 37.77954989760758,
                "longitude": -122.42116599596605
            }
        },
        {
            "timestamp": "2024-10-16T04:20:21Z",
            "position": {
                "latitude": 37.7794281662979,
                "longitude": -122.42101519698299
            }
        }
    ],
    "pathPrediction": {
        "timestamp": "2024-10-16T04:21:36Z",
        "position": {
            "latitude": 37.77896192655881,
            "longitude": -122.421758987969
        },
        "confidence": 0.556162430256796
    }
}