{
    "messageType": "BSM",
    "messageId": "9_261",
    "messageCount": 261,
    "vehicleId": "9",
    "timestamp": "2024-10-16T04:22:58Z",
    "position": {
        "latitude": 37.76588039708939,
        "longitude": -122.42148449457045,
        "altitude": 18.738246558793733
    },
    "speed": 42.26999742996141,
    "heading": 215.91326274560168,
    "acceleration": {
        "x": 0.20244188336594404,
        "y": -0.40678306206983206,
        "z": 0.14624234046952744
    },
    "brakeStatus": false,
    "vehicleSize": {
        "length": 4.506554848903611,
        "width": 2.101293547105982
    },
    "pathHistory": [
        {
            "timestamp": "2024-10-16T04:22:28Z",
            "position": {
                "latitude": 37.765871835238165,
                "longitude": -122.42148741865786
            }
        },
        {
            "timestamp": "2024-10-16T04:21:58Z",
            "position": {
                "latitude": 37.76571731549748,
                "longitude": -122.4215008041671
            }
        }
    ],
    "pathPrediction": {
        "timestamp": "2024-10-16T04:23:13Z",
        "position": {
            "latitude": 37.766447886214735,
            "longitude": -122.4208737621716
        },
        "confidence": 0.520342957719071
    }
}