{
    "messageType": "BSM",
    "messageId": "9_657",
    "messageCount": 657,
    "vehicleId": "9",
    "timestamp": "2024-10-16T04:22:11Z",
    "position": {
        "latitude": 37.77714262361903,
        "longitude": -122.4152939174581,
        "altitude": 15.247493335757854
    },
    "speed": 79.82591873278653,
    "heading": 149.51503130711862,
    "acceleration": {
        "x": 0.037223774241986085,
        "y": -0.27163831999928423,
        "z": -0.44346226467630734
    },
    "brakeStatus": false,
    "vehicleSize": {
        "length": 3.696338788154732,
        "width": 2.29120661193276
    },
    "pathHistory": [
        {
            "timestamp": "2024-10-16T04:21:41Z",
            "position": {
                "latitude": 37.77711204952911,
                "longitude": -122.41520747531553
            }
        },
        {
            "timestamp": "2024-10-16T04:21:11Z",
            "position": {
                "latitude": 37.77730829553419,
                "longitude": -122.41540341304243
            }
        }
    ],
    "pathPrediction": {
        "timestamp": "2024-10-16T04:22:26Z",
        "position": {
            "latitude": 37.77775529111435,
            "longitude": -122.41526041027419
        },
        "confidence": 0.9221869791104524
    }
}