{
    "messageType": "BSM",
    "messageId": "6_110",
    "messageCount": 110,
    "vehicleId": "6",
    "timestamp": "2024-10-16T04:23:42Z",
    "position": {
        "latitude": 37.76823424264605,
        "longitude": -122.42444918998434,
        "altitude": 18.84268868683894
    },
    "speed": 67.86824324785312,
    "heading": 173.82985480764904,
    "acceleration": {
        "x": -0.8910929774507435,
        "y": 0.873389836470555,
        "z": 0.4237732999933861
    },
    "brakeStatus": true,
    "vehicleSize": {
        "length": 3.7453547859536274,
        "width": 1.9022409495597108
    },
    "pathHistory": [
        {
            "timestamp": "2024-10-16T04:23:12Z",
            "position": {
                "latitude": 37.76815429066976,
                "longitude": -122.42447735278682
            }
        },
        {
            "timestamp": "2024-10-16T04:22:42Z",
            "position": {
                "latitude": 37.768303404161486,
                "longitude": -122.4244500690691
            }
        }
    ],
    "pathPrediction": {
        "timestamp": "2024-10-16T04:23:57Z",
        "position": {
            "latitude": 37.76858596486596,
            "longitude": -122.42379880550784
        },
        "confidence": 0.9173150460426664
    },
    "receivingPosition": {
        "latitude": 37.7743612765109,
        "longitude": -122.42818638761987,
        "altitude": 27.457952761184437
    },
    "receivedPower": 1.600577193726625e-06
}